{
  "dApp": "3N6LHjfGb6Fgcy7YsVcNxGyPTj49XbQAijq",
  "version": 2,
  "type": 12,
  "chainId": 87,
  "fee": 500000,
  "proofs": [],
  "timestamp": 0,
  "senderPublicKey": "2VkbtS8CodmbZqAounEpDSf4dAfLoCWfEEGHZK7qtbeD",
  "data": [
    {
      "type": "string",
      "value": "3N4nTJ5sSp5X5ChS2bBBmwNMn1eeRzT1FoP",
      "key": "%s__feeProtocolContractAddress"
    },
    {
      "type": "string",
      "value": "3MsMP2pb2p8MDd6Rxb7XEXqqwEhE8ATfyai",
      "key": "%s__factoryContract"
    },
    {
      "type": "integer",
      "value": 1000,
      "key": "%s__protocolFee"
    }
  ]
}
  